r2/__init__.py
"r2/__main__.,py"
r2/cli.py
r2/files.py
r2/py.typed
r2_assistant-0.1.0.dist-info/METADATA
r2_assistant-0.1.0.dist-info/WHEEL
r2_assistant-0.1.0.dist-info/entry_points.txt
r2_assistant-0.1.0.dist-info/RECORD
