Metadata-Version: 2.4
Name: r2-assistant
Version: 0.1.0
Summary: A collection of tools to help managing a very opinionated Linux setup.
Author-email: Fábio Macêdo Mendes <fabiomacedomendes@gmail.com>
Requires-Python: >=3.13
Requires-Dist: rich>=14.2.0
Requires-Dist: typer>=0.20.0
